flake8_absolute_import/__init__.py
flake8_absolute_import/core.py
flake8_absolute_import/version.py
flake8_absolute_import-1.0.0.2.dist-info/LICENSE.txt
flake8_absolute_import-1.0.0.2.dist-info/METADATA
flake8_absolute_import-1.0.0.2.dist-info/WHEEL
flake8_absolute_import-1.0.0.2.dist-info/entry_points.txt
flake8_absolute_import-1.0.0.2.dist-info/top_level.txt
flake8_absolute_import-1.0.0.2.dist-info/RECORD
