Metadata-Version: 2.1
Name: flake8-absolute-import
Version: 1.0.0.2
Summary: flake8 plugin to require absolute imports
Author-email: Brian Skinn <brian.skinn@gmail.com>
License: MIT License
Project-URL: Homepage, https://github.com/bskinn/flake8-absolute-import
Project-URL: Changelog, https://github.com/bskinn/flake8-absolute-import/blob/main/CHANGELOG.md
Project-URL: Thank, https://twitter.com/btskinn
Project-URL: Donate, https://github.com/sponsors/bskinn
Keywords: flake8-plugin,linting,absolute-imports,relative-imports
Platform: any
Classifier: License :: OSI Approved
Classifier: License :: OSI Approved :: MIT License
Classifier: Natural Language :: English
Classifier: Framework :: Flake8
Classifier: Intended Audience :: Developers
Classifier: Operating System :: OS Independent
Classifier: Programming Language :: Python
Classifier: Programming Language :: Python :: 3
Classifier: Programming Language :: Python :: 3 :: Only
Classifier: Programming Language :: Python :: 3.8
Classifier: Programming Language :: Python :: 3.9
Classifier: Programming Language :: Python :: 3.10
Classifier: Programming Language :: Python :: 3.11
Classifier: Programming Language :: Python :: 3.12
Classifier: Topic :: Software Development :: Quality Assurance
Classifier: Development Status :: 5 - Production/Stable
Requires-Python: >=3.6
License-File: LICENSE.txt
Requires-Dist: flake8>=5.0
